comoneo.cp36-win_amd64.pyd
comoneo-0.0.1.dist-info/METADATA
comoneo-0.0.1.dist-info/WHEEL
comoneo-0.0.1.dist-info/top_level.txt
comoneo-0.0.1.dist-info/RECORD
