Metadata-Version: 2.1
Name: comoneo
Version: 0.0.1
Summary: comoneo
Home-page: UNKNOWN
Author: Danian Hu
Author-email: hudanian@hotmail.com
License: UNKNOWN
Platform: UNKNOWN
